csv_reconcile_fingerprint/__init__.py
csv_reconcile_fingerprint/utils.py
csv_reconcile_fingerprint-0.1.8.dist-info/licenses/LICENSE
csv_reconcile_fingerprint-0.1.8.dist-info/METADATA
csv_reconcile_fingerprint-0.1.8.dist-info/WHEEL
csv_reconcile_fingerprint-0.1.8.dist-info/entry_points.txt
csv_reconcile_fingerprint-0.1.8.dist-info/top_level.txt
csv_reconcile_fingerprint-0.1.8.dist-info/RECORD
