Metadata-Version: 2.4
Name: csv-reconcile-fingerprint
Version: 0.1.8
Summary: A scoring plugin for csv-reconcile using fingerprint clustering.
Author: Katharina Brunner
License: Apache-2.0
Project-URL: Homepage, https://github.com/cutterkom/csv-reconcile-fingerprint
Project-URL: Changelog, https://github.com/cutterkom/csv-reconcile-fingerprint/releases
Project-URL: Issues, https://github.com/cutterkom/csv-reconcile-fingerprint/issues
Project-URL: CI, https://github.com/cutterkom/csv-reconcile-fingerprint/actions
Classifier: License :: OSI Approved :: Apache Software License
Requires-Python: >=3.8
License-File: LICENSE
Requires-Dist: csv-reconcile
Requires-Dist: unidecode
Provides-Extra: test
Requires-Dist: pytest; extra == "test"
Dynamic: license-file
